{
    "id": "44",
    "segmentNrInTask": "4",
    "fileId": "5",
    "userGuid": "{00000000-0000-0000-C100-CCDDEE000002}",
    "userName": "lector test",
    "taskGuid": "{c446f382-e5f0-48ea-af55-f4fce0b5e698}",
    "timestamp": "2025-07-09 12:44:27",
    "editable": "1",
    "pretrans": "0",
    "matchRate": "0",
    "matchRateType": "import;none",
    "penaltyGeneral": "0",
    "penaltySublang": "0",
    "stateId": "0",
    "autoStateId": "1",
    "fileOrder": "0",
    "comments": null,
    "workflowStepNr": "1",
    "workflowStep": "reviewing",
    "isRepeated": "3",
    "levenshteinOriginal": "0",
    "levenshteinPrevious": "0",
    "editedInStep": "",
    "source": "<div class=\"open 672069643d2233343322 internal-tag ownttip\"><span class=\"short\" title=\"&lt;strong class=&quot;note&quot;&gt;\">&lt;1&gt;</span><span class=\"full\" data-originalid=\"343\" data-length=\"-1\">&lt;strong class=&quot;note&quot;&gt;</span></div>Note<div class=\"close 2f67 internal-tag ownttip\"><span class=\"short\" title=\"&lt;/strong&gt;\">&lt;/1&gt;</span><span class=\"full\" data-originalid=\"343\" data-length=\"-1\">&lt;/strong&gt;</span></div>:",
    "sourceMd5": "5875ec9c77ae25b21199543741007f3f",
    "sourceToSort": "Note:",
    "target": "<div class=\"open 672069643d2233343322 internal-tag ownttip\"><span class=\"short\" title=\"&lt;strong class=&quot;note&quot;&gt;\">&lt;1&gt;</span><span class=\"full\" data-originalid=\"343\" data-length=\"-1\">&lt;strong class=&quot;note&quot;&gt;</span></div>Hinweis<div class=\"close 2f67 internal-tag ownttip\"><span class=\"short\" title=\"&lt;/strong&gt;\">&lt;/1&gt;</span><span class=\"full\" data-originalid=\"343\" data-length=\"-1\">&lt;/strong&gt;</span></div>:",
    "targetMd5": "9715c7a12418ab4cd09848d3919a7a41",
    "targetToSort": "Hinweis:",
    "targetEdit": "<div class=\"close 2f67 internal-tag ownttip\"><span class=\"short\" title=\"&lt;/strong&gt;\">&lt;/1&gt;</span><span class=\"full\" data-originalid=\"343\" data-length=\"-1\">&lt;/strong&gt;</span></div>Hinweis<div class=\"open 672069643d2233343322 internal-tag ownttip\"><span class=\"short\" title=\"&lt;strong class=&quot;note&quot;&gt;\">&lt;1&gt;</span><span class=\"full\" data-originalid=\"343\" data-length=\"-1\">&lt;strong class=&quot;note&quot;&gt;</span></div>:",
    "targetEditToSort": "Hinweis:",
    "isWatched": null,
    "segmentUserAssocId": null,
    "metaCache": "{\"minWidth\":null,\"maxWidth\":null,\"maxNumberOfLines\":null,\"sizeUnit\":\"\",\"font\":\"\",\"fontSize\":0,\"additionalUnitLength\":0,\"additionalMrkLength\":0,\"siblingData\":{\"44\": {\"nr\":\"4\",\"length\":{\"targetEdit\":8}}}}",
    "spellCheck": {}
}